wavelet_buffer/__init__.py
wavelet_buffer/wavelet_buffer.py
wavelet_buffer/_wavelet_buffer.cpython-39-x86_64-linux-gnu.so
wavelet_buffer/denoise.py
wavelet_buffer/utils.py
wavelet_buffer/wavelet_buffer_view.py
wavelet_buffer/include/streamvbyte.h
wavelet_buffer/include/streamvbytedelta.h
wavelet_buffer/include/fpzip.h
wavelet_buffer/include/streamvbyte_zigzag.h
wavelet_buffer/include/wavelet_buffer/wavelet.h
wavelet_buffer/include/wavelet_buffer/wavelet_buffer.h
wavelet_buffer/include/wavelet_buffer/wavelet_parameters.h
wavelet_buffer/include/wavelet_buffer/primitives.h
wavelet_buffer/include/wavelet_buffer/padding.h
wavelet_buffer/include/wavelet_buffer/denoise_algorithms.h
wavelet_buffer/include/wavelet_buffer/wavelet_buffer_serializer.h
wavelet_buffer/include/wavelet_buffer/wavelet_buffer_view.h
wavelet_buffer/include/wavelet_buffer/wavelet_utils.h
wavelet_buffer/include/wavelet_buffer/img/image_codec.h
wavelet_buffer/include/wavelet_buffer/img/wavelet_image.h
wavelet_buffer/include/wavelet_buffer/img/color_space.h
wavelet_buffer/include/wavelet_buffer/img/jpeg_codecs.h
wavelet_buffer/lib/libstreamvbyte.a
wavelet_buffer/share/wavelet_buffer/cmake/wavelet_buffer-config.cmake
wavelet_buffer/share/wavelet_buffer/cmake/wavelet_buffer-targets.cmake
wavelet_buffer/share/wavelet_buffer/cmake/wavelet_buffer-targets-release.cmake
wavelet_buffer/share/wavelet_buffer/cmake/wavelet_buffer-config-version.cmake
wavelet_buffer/lib64/libfpzip.a
wavelet_buffer/lib64/libwavelet_buffer.a
wavelet_buffer/lib64/libstreamvbyte.a
wavelet_buffer/lib64/cmake/fpzip/fpzip-targets-release.cmake
wavelet_buffer/lib64/cmake/fpzip/fpzip-config.cmake
wavelet_buffer/lib64/cmake/fpzip/fpzip-config-version.cmake
wavelet_buffer/lib64/cmake/fpzip/fpzip-targets.cmake
wavelet_buffer/img/__init__.py
wavelet_buffer/img/wavelet_image.py
wavelet_buffer/img/codecs.py
wavelet_buffer-0.7.1.dist-info/RECORD
wavelet_buffer-0.7.1.dist-info/AUTHORS.md
wavelet_buffer-0.7.1.dist-info/LICENSE
wavelet_buffer-0.7.1.dist-info/WHEEL
wavelet_buffer-0.7.1.dist-info/METADATA
wavelet_buffer-0.7.1.dist-info/top_level.txt
