Metadata-Version: 2.1
Name: wavelet-buffer
Version: 0.7.1
Summary: A universal C++ compression library based on wavelet transformation
Home-page: https://github.com/panda-official/WaveletBuffer
Author: PANDA, GmbH
Author-email: info@panda.technology
License: MPL-2.0
Classifier: Development Status :: 4 - Beta
Classifier: Intended Audience :: Science/Research
Classifier: Intended Audience :: Developers
Classifier: License :: OSI Approved :: Mozilla Public License 2.0 (MPL 2.0)
Classifier: Operating System :: Unix
Classifier: Programming Language :: Python :: 3
Classifier: Programming Language :: Python :: 3.8
Classifier: Programming Language :: Python :: 3.9
Classifier: Programming Language :: Python :: 3.10
Classifier: Programming Language :: Python :: 3.11
Classifier: Programming Language :: Python :: 3 :: Only
Classifier: Programming Language :: Python :: Implementation :: CPython
Classifier: Topic :: Software Development
Classifier: Topic :: Scientific/Engineering
Requires-Python: >=3.8
License-File: LICENSE
License-File: AUTHORS.md
